tabb/__about__.py
tabb/__init__.py
tabb/base.py
tabb/callback.py
tabb/command.py
tabb/config.py
tabb/context.py
tabb/decorators.py
tabb/exceptions.py
tabb/formatter.py
tabb/group.py
tabb/missing.py
tabb/nargs.py
tabb/parser.py
tabb/py.typed
tabb/scheduler.py
tabb/types.py
tabb/utils.py
tabb/parameter/__init__.py
tabb/parameter/base.py
tabb/parameter/depends.py
tabb/parameter/group.py
tabb/parameter/parser.py
tabb/parameter/resolve.py
tabb/parameter/types.py
tabb/parameter/utils.py
tabb-0.5.1.dist-info/METADATA
tabb-0.5.1.dist-info/WHEEL
tabb-0.5.1.dist-info/licenses/LICENSE.txt
tabb-0.5.1.dist-info/RECORD
