Metadata-Version: 2.1
Name: tabb
Version: 0.5.1
Summary: Trevor's argparse but better.
Project-URL: Documentation, https://github.com/wtolson/tabb#readme
Project-URL: Issues, https://github.com/wtolson/tabb/issues
Project-URL: Source, https://github.com/wtolson/tabb
Author-email: Trevor Olson <trevor@heytrevor.com>
License-Expression: MIT
License-File: LICENSE.txt
Classifier: Development Status :: 3 - Alpha
Classifier: Intended Audience :: Developers
Classifier: License :: OSI Approved :: MIT License
Classifier: Natural Language :: English
Classifier: Programming Language :: Python
Classifier: Programming Language :: Python :: 3.10
Classifier: Programming Language :: Python :: 3.11
Classifier: Typing :: Typed
Requires-Python: >=3.10
